ANotify/Nanpush.py
ANotify/Nbemfa.py
ANotify/Nchuanxi.py
ANotify/Ndingtalk.py
ANotify/Nemail.py
ANotify/Nfeishu.py
ANotify/Ngotify.py
ANotify/Niyuu.py
ANotify/Nntfy.py
ANotify/Npushplus.py
ANotify/Nreminder.py
ANotify/Nresend.py
ANotify/Nserverchan.py
ANotify/Ntelegram.py
ANotify/Nwecom.py
ANotify/Nwpush.py
ANotify/Nxizhi.py
ANotify/__init__.py
anotify-0.2.2.dist-info/licenses/LICENSE
anotify-0.2.2.dist-info/METADATA
anotify-0.2.2.dist-info/WHEEL
anotify-0.2.2.dist-info/top_level.txt
anotify-0.2.2.dist-info/RECORD
