Metadata-Version: 2.4
Name: anotify
Version: 0.2.2
Summary: Send notifications by multiple channels
Home-page: https://github.com/TommyMerlin/ANotify
Author: 7ommy
Author-email: tommymerlin0920@gmail.com
License: MIT
Classifier: Programming Language :: Python :: 3
Classifier: License :: OSI Approved :: MIT License
Requires-Python: >=3.7
License-File: LICENSE
Requires-Dist: requests>=2.15.1
Requires-Dist: httpx>=0.26.0
Requires-Dist: resend>=2.10.0
Dynamic: author
Dynamic: author-email
Dynamic: classifier
Dynamic: description
Dynamic: description-content-type
Dynamic: home-page
Dynamic: license
Dynamic: license-file
Dynamic: requires-dist
Dynamic: requires-python
Dynamic: summary
